bodysnatcher/__init__.py
bodysnatcher/_bodysnatcher.py
bodysnatcher/py.typed
bodysnatcher-0.1.1.dist-info/METADATA
bodysnatcher-0.1.1.dist-info/WHEEL
bodysnatcher-0.1.1.dist-info/licenses/LICENCE
bodysnatcher-0.1.1.dist-info/RECORD
