Metadata-Version: 2.3
Name: bodysnatcher
Version: 0.1.1
Summary: Save objects when an exception occurs using pickle.
Author-email: Tom Kuson <mail@tjkuson.me>
License: MIT
License-File: LICENCE
Requires-Python: >=3.9
Requires-Dist: typing-extensions>=4.11.0
